{
  "$schema": "../../schema/sprite-pack.schema.json",
  "id": "1-bit-pack",
  "name": "1-Bit Pack",
  "source": "kenney",
  "license": "CC0",
  "homepage": "https://kenney.nl/assets/1-bit-pack",
  "downloadUrl": "https://kenney.nl/media/pages/assets/1-bit-pack/f41b6925f0-1677578516/kenney_1-bit-pack.zip",

  "tileSize": 16,
  "primarySheet": "Tilesheet/monochrome_packed.png",

  "metadata": {
    "author": "Kenney",
    "description": "Monochrome 1-bit pixel art tileset (16x16) - 1078 tiles covering platformer, interior, urban, and fantasy themes. Also includes colored variant.",
    "totalAssets": 1078,
    "gridSize": { "cols": 49, "rows": 22 },
    "variants": {
      "monochrome": "Tilesheet/monochrome_packed.png",
      "monochrome-transparent": "Tilesheet/monochrome-transparent_packed.png",
      "colored": "Tilesheet/colored_packed.png",
      "colored-transparent": "Tilesheet/colored-transparent_packed.png"
    }
  },

  "sprites": {
    "tile-0000": { "x": 0, "y": 0 },
    "tile-0001": { "x": 16, "y": 0 },
    "tile-0002": { "x": 32, "y": 0 },
    "tile-0003": { "x": 48, "y": 0 },
    "tile-0004": { "x": 64, "y": 0 },
    "tile-0005": { "x": 80, "y": 0 },
    "tile-0006": { "x": 96, "y": 0 },
    "tile-0007": { "x": 112, "y": 0 },
    "tile-0008": { "x": 128, "y": 0 },
    "tile-0009": { "x": 144, "y": 0 },
    "tile-0010": { "x": 160, "y": 0 },
    "tile-0011": { "x": 176, "y": 0 },
    "tile-0012": { "x": 192, "y": 0 },
    "tile-0013": { "x": 208, "y": 0 },
    "tile-0014": { "x": 224, "y": 0 },
    "tile-0015": { "x": 240, "y": 0 },
    "tile-0016": { "x": 256, "y": 0 },
    "tile-0017": { "x": 272, "y": 0 },
    "tile-0018": { "x": 288, "y": 0 },
    "tile-0019": { "x": 304, "y": 0 },
    "tile-0020": { "x": 320, "y": 0 },
    "tile-0021": { "x": 336, "y": 0 },
    "tile-0022": { "x": 352, "y": 0 },
    "tile-0023": { "x": 368, "y": 0 },
    "tile-0024": { "x": 384, "y": 0 },
    "tile-0025": { "x": 400, "y": 0 },
    "tile-0026": { "x": 416, "y": 0 },
    "tile-0027": { "x": 432, "y": 0 },
    "tile-0028": { "x": 448, "y": 0 },
    "tile-0029": { "x": 464, "y": 0 },
    "tile-0030": { "x": 480, "y": 0 },
    "tile-0031": { "x": 496, "y": 0 },
    "tile-0032": { "x": 512, "y": 0 },
    "tile-0033": { "x": 528, "y": 0 },
    "tile-0034": { "x": 544, "y": 0 },
    "tile-0035": { "x": 560, "y": 0 },
    "tile-0036": { "x": 576, "y": 0 },
    "tile-0037": { "x": 592, "y": 0 },
    "tile-0038": { "x": 608, "y": 0 },
    "tile-0039": { "x": 624, "y": 0 },
    "tile-0040": { "x": 640, "y": 0 },
    "tile-0041": { "x": 656, "y": 0 },
    "tile-0042": { "x": 672, "y": 0 },
    "tile-0043": { "x": 688, "y": 0 },
    "tile-0044": { "x": 704, "y": 0 },
    "tile-0045": { "x": 720, "y": 0 },
    "tile-0046": { "x": 736, "y": 0 },
    "tile-0047": { "x": 752, "y": 0 },
    "tile-0048": { "x": 768, "y": 0 },
    "tile-0049": { "x": 0, "y": 16 },
    "tile-0050": { "x": 16, "y": 16 },
    "tile-0051": { "x": 32, "y": 16 },
    "tile-0052": { "x": 48, "y": 16 },
    "tile-0053": { "x": 64, "y": 16 },
    "tile-0054": { "x": 80, "y": 16 },
    "tile-0055": { "x": 96, "y": 16 },
    "tile-0056": { "x": 112, "y": 16 },
    "tile-0057": { "x": 128, "y": 16 },
    "tile-0058": { "x": 144, "y": 16 },
    "tile-0059": { "x": 160, "y": 16 },
    "tile-0060": { "x": 176, "y": 16 },
    "tile-0061": { "x": 192, "y": 16 },
    "tile-0062": { "x": 208, "y": 16 },
    "tile-0063": { "x": 224, "y": 16 },
    "tile-0064": { "x": 240, "y": 16 },
    "tile-0065": { "x": 256, "y": 16 },
    "tile-0066": { "x": 272, "y": 16 },
    "tile-0067": { "x": 288, "y": 16 },
    "tile-0068": { "x": 304, "y": 16 },
    "tile-0069": { "x": 320, "y": 16 },
    "tile-0070": { "x": 336, "y": 16 },
    "tile-0071": { "x": 352, "y": 16 },
    "tile-0072": { "x": 368, "y": 16 },
    "tile-0073": { "x": 384, "y": 16 },
    "tile-0074": { "x": 400, "y": 16 },
    "tile-0075": { "x": 416, "y": 16 },
    "tile-0076": { "x": 432, "y": 16 },
    "tile-0077": { "x": 448, "y": 16 },
    "tile-0078": { "x": 464, "y": 16 },
    "tile-0079": { "x": 480, "y": 16 },
    "tile-0080": { "x": 496, "y": 16 },
    "tile-0081": { "x": 512, "y": 16 },
    "tile-0082": { "x": 528, "y": 16 },
    "tile-0083": { "x": 544, "y": 16 },
    "tile-0084": { "x": 560, "y": 16 },
    "tile-0085": { "x": 576, "y": 16 },
    "tile-0086": { "x": 592, "y": 16 },
    "tile-0087": { "x": 608, "y": 16 },
    "tile-0088": { "x": 624, "y": 16 },
    "tile-0089": { "x": 640, "y": 16 },
    "tile-0090": { "x": 656, "y": 16 },
    "tile-0091": { "x": 672, "y": 16 },
    "tile-0092": { "x": 688, "y": 16 },
    "tile-0093": { "x": 704, "y": 16 },
    "tile-0094": { "x": 720, "y": 16 },
    "tile-0095": { "x": 736, "y": 16 },
    "tile-0096": { "x": 752, "y": 16 },
    "tile-0097": { "x": 768, "y": 16 },
    "tile-0098": { "x": 0, "y": 32 },
    "tile-0099": { "x": 16, "y": 32 },
    "tile-0100": { "x": 32, "y": 32 },
    "tile-0101": { "x": 48, "y": 32 },
    "tile-0102": { "x": 64, "y": 32 },
    "tile-0103": { "x": 80, "y": 32 },
    "tile-0104": { "x": 96, "y": 32 },
    "tile-0105": { "x": 112, "y": 32 },
    "tile-0106": { "x": 128, "y": 32 },
    "tile-0107": { "x": 144, "y": 32 },
    "tile-0108": { "x": 160, "y": 32 },
    "tile-0109": { "x": 176, "y": 32 },
    "tile-0110": { "x": 192, "y": 32 },
    "tile-0111": { "x": 208, "y": 32 },
    "tile-0112": { "x": 224, "y": 32 },
    "tile-0113": { "x": 240, "y": 32 },
    "tile-0114": { "x": 256, "y": 32 },
    "tile-0115": { "x": 272, "y": 32 },
    "tile-0116": { "x": 288, "y": 32 },
    "tile-0117": { "x": 304, "y": 32 },
    "tile-0118": { "x": 320, "y": 32 },
    "tile-0119": { "x": 336, "y": 32 },
    "tile-0120": { "x": 352, "y": 32 },
    "tile-0121": { "x": 368, "y": 32 },
    "tile-0122": { "x": 384, "y": 32 },
    "tile-0123": { "x": 400, "y": 32 },
    "tile-0124": { "x": 416, "y": 32 },
    "tile-0125": { "x": 432, "y": 32 },
    "tile-0126": { "x": 448, "y": 32 },
    "tile-0127": { "x": 464, "y": 32 },
    "tile-0128": { "x": 480, "y": 32 },
    "tile-0129": { "x": 496, "y": 32 },
    "tile-0130": { "x": 512, "y": 32 },
    "tile-0131": { "x": 528, "y": 32 },
    "tile-0132": { "x": 544, "y": 32 },
    "tile-0133": { "x": 560, "y": 32 },
    "tile-0134": { "x": 576, "y": 32 },
    "tile-0135": { "x": 592, "y": 32 },
    "tile-0136": { "x": 608, "y": 32 },
    "tile-0137": { "x": 624, "y": 32 },
    "tile-0138": { "x": 640, "y": 32 },
    "tile-0139": { "x": 656, "y": 32 },
    "tile-0140": { "x": 672, "y": 32 },
    "tile-0141": { "x": 688, "y": 32 },
    "tile-0142": { "x": 704, "y": 32 },
    "tile-0143": { "x": 720, "y": 32 },
    "tile-0144": { "x": 736, "y": 32 },
    "tile-0145": { "x": 752, "y": 32 },
    "tile-0146": { "x": 768, "y": 32 },
    "tile-0147": { "x": 0, "y": 48 },
    "tile-0148": { "x": 16, "y": 48 },
    "tile-0149": { "x": 32, "y": 48 },
    "tile-0150": { "x": 48, "y": 48 },
    "tile-0151": { "x": 64, "y": 48 },
    "tile-0152": { "x": 80, "y": 48 },
    "tile-0153": { "x": 96, "y": 48 },
    "tile-0154": { "x": 112, "y": 48 },
    "tile-0155": { "x": 128, "y": 48 },
    "tile-0156": { "x": 144, "y": 48 },
    "tile-0157": { "x": 160, "y": 48 },
    "tile-0158": { "x": 176, "y": 48 },
    "tile-0159": { "x": 192, "y": 48 },
    "tile-0160": { "x": 208, "y": 48 },
    "tile-0161": { "x": 224, "y": 48 },
    "tile-0162": { "x": 240, "y": 48 },
    "tile-0163": { "x": 256, "y": 48 },
    "tile-0164": { "x": 272, "y": 48 },
    "tile-0165": { "x": 288, "y": 48 },
    "tile-0166": { "x": 304, "y": 48 },
    "tile-0167": { "x": 320, "y": 48 },
    "tile-0168": { "x": 336, "y": 48 },
    "tile-0169": { "x": 352, "y": 48 },
    "tile-0170": { "x": 368, "y": 48 },
    "tile-0171": { "x": 384, "y": 48 },
    "tile-0172": { "x": 400, "y": 48 },
    "tile-0173": { "x": 416, "y": 48 },
    "tile-0174": { "x": 432, "y": 48 },
    "tile-0175": { "x": 448, "y": 48 },
    "tile-0176": { "x": 464, "y": 48 },
    "tile-0177": { "x": 480, "y": 48 },
    "tile-0178": { "x": 496, "y": 48 },
    "tile-0179": { "x": 512, "y": 48 },
    "tile-0180": { "x": 528, "y": 48 },
    "tile-0181": { "x": 544, "y": 48 },
    "tile-0182": { "x": 560, "y": 48 },
    "tile-0183": { "x": 576, "y": 48 },
    "tile-0184": { "x": 592, "y": 48 },
    "tile-0185": { "x": 608, "y": 48 },
    "tile-0186": { "x": 624, "y": 48 },
    "tile-0187": { "x": 640, "y": 48 },
    "tile-0188": { "x": 656, "y": 48 },
    "tile-0189": { "x": 672, "y": 48 },
    "tile-0190": { "x": 688, "y": 48 },
    "tile-0191": { "x": 704, "y": 48 },
    "tile-0192": { "x": 720, "y": 48 },
    "tile-0193": { "x": 736, "y": 48 },
    "tile-0194": { "x": 752, "y": 48 },
    "tile-0195": { "x": 768, "y": 48 },
    "tile-0196": { "x": 0, "y": 64 },
    "tile-0197": { "x": 16, "y": 64 },
    "tile-0198": { "x": 32, "y": 64 },
    "tile-0199": { "x": 48, "y": 64 },
    "tile-0200": { "x": 64, "y": 64 },
    "tile-0201": { "x": 80, "y": 64 },
    "tile-0202": { "x": 96, "y": 64 },
    "tile-0203": { "x": 112, "y": 64 },
    "tile-0204": { "x": 128, "y": 64 },
    "tile-0205": { "x": 144, "y": 64 },
    "tile-0206": { "x": 160, "y": 64 },
    "tile-0207": { "x": 176, "y": 64 },
    "tile-0208": { "x": 192, "y": 64 },
    "tile-0209": { "x": 208, "y": 64 },
    "tile-0210": { "x": 224, "y": 64 },
    "tile-0211": { "x": 240, "y": 64 },
    "tile-0212": { "x": 256, "y": 64 },
    "tile-0213": { "x": 272, "y": 64 },
    "tile-0214": { "x": 288, "y": 64 },
    "tile-0215": { "x": 304, "y": 64 },
    "tile-0216": { "x": 320, "y": 64 },
    "tile-0217": { "x": 336, "y": 64 },
    "tile-0218": { "x": 352, "y": 64 },
    "tile-0219": { "x": 368, "y": 64 },
    "tile-0220": { "x": 384, "y": 64 },
    "tile-0221": { "x": 400, "y": 64 },
    "tile-0222": { "x": 416, "y": 64 },
    "tile-0223": { "x": 432, "y": 64 },
    "tile-0224": { "x": 448, "y": 64 },
    "tile-0225": { "x": 464, "y": 64 },
    "tile-0226": { "x": 480, "y": 64 },
    "tile-0227": { "x": 496, "y": 64 },
    "tile-0228": { "x": 512, "y": 64 },
    "tile-0229": { "x": 528, "y": 64 },
    "tile-0230": { "x": 544, "y": 64 },
    "tile-0231": { "x": 560, "y": 64 },
    "tile-0232": { "x": 576, "y": 64 },
    "tile-0233": { "x": 592, "y": 64 },
    "tile-0234": { "x": 608, "y": 64 },
    "tile-0235": { "x": 624, "y": 64 },
    "tile-0236": { "x": 640, "y": 64 },
    "tile-0237": { "x": 656, "y": 64 },
    "tile-0238": { "x": 672, "y": 64 },
    "tile-0239": { "x": 688, "y": 64 },
    "tile-0240": { "x": 704, "y": 64 },
    "tile-0241": { "x": 720, "y": 64 },
    "tile-0242": { "x": 736, "y": 64 },
    "tile-0243": { "x": 752, "y": 64 },
    "tile-0244": { "x": 768, "y": 64 },
    "tile-0245": { "x": 0, "y": 80 },
    "tile-0246": { "x": 16, "y": 80 },
    "tile-0247": { "x": 32, "y": 80 },
    "tile-0248": { "x": 48, "y": 80 },
    "tile-0249": { "x": 64, "y": 80 },
    "tile-0250": { "x": 80, "y": 80 },
    "tile-0251": { "x": 96, "y": 80 },
    "tile-0252": { "x": 112, "y": 80 },
    "tile-0253": { "x": 128, "y": 80 },
    "tile-0254": { "x": 144, "y": 80 },
    "tile-0255": { "x": 160, "y": 80 },
    "tile-0256": { "x": 176, "y": 80 },
    "tile-0257": { "x": 192, "y": 80 },
    "tile-0258": { "x": 208, "y": 80 },
    "tile-0259": { "x": 224, "y": 80 },
    "tile-0260": { "x": 240, "y": 80 },
    "tile-0261": { "x": 256, "y": 80 },
    "tile-0262": { "x": 272, "y": 80 },
    "tile-0263": { "x": 288, "y": 80 },
    "tile-0264": { "x": 304, "y": 80 },
    "tile-0265": { "x": 320, "y": 80 },
    "tile-0266": { "x": 336, "y": 80 },
    "tile-0267": { "x": 352, "y": 80 },
    "tile-0268": { "x": 368, "y": 80 },
    "tile-0269": { "x": 384, "y": 80 },
    "tile-0270": { "x": 400, "y": 80 },
    "tile-0271": { "x": 416, "y": 80 },
    "tile-0272": { "x": 432, "y": 80 },
    "tile-0273": { "x": 448, "y": 80 },
    "tile-0274": { "x": 464, "y": 80 },
    "tile-0275": { "x": 480, "y": 80 },
    "tile-0276": { "x": 496, "y": 80 },
    "tile-0277": { "x": 512, "y": 80 },
    "tile-0278": { "x": 528, "y": 80 },
    "tile-0279": { "x": 544, "y": 80 },
    "tile-0280": { "x": 560, "y": 80 },
    "tile-0281": { "x": 576, "y": 80 },
    "tile-0282": { "x": 592, "y": 80 },
    "tile-0283": { "x": 608, "y": 80 },
    "tile-0284": { "x": 624, "y": 80 },
    "tile-0285": { "x": 640, "y": 80 },
    "tile-0286": { "x": 656, "y": 80 },
    "tile-0287": { "x": 672, "y": 80 },
    "tile-0288": { "x": 688, "y": 80 },
    "tile-0289": { "x": 704, "y": 80 },
    "tile-0290": { "x": 720, "y": 80 },
    "tile-0291": { "x": 736, "y": 80 },
    "tile-0292": { "x": 752, "y": 80 },
    "tile-0293": { "x": 768, "y": 80 },
    "tile-0294": { "x": 0, "y": 96 },
    "tile-0295": { "x": 16, "y": 96 },
    "tile-0296": { "x": 32, "y": 96 },
    "tile-0297": { "x": 48, "y": 96 },
    "tile-0298": { "x": 64, "y": 96 },
    "tile-0299": { "x": 80, "y": 96 },
    "tile-0300": { "x": 96, "y": 96 },
    "tile-0301": { "x": 112, "y": 96 },
    "tile-0302": { "x": 128, "y": 96 },
    "tile-0303": { "x": 144, "y": 96 },
    "tile-0304": { "x": 160, "y": 96 },
    "tile-0305": { "x": 176, "y": 96 },
    "tile-0306": { "x": 192, "y": 96 },
    "tile-0307": { "x": 208, "y": 96 },
    "tile-0308": { "x": 224, "y": 96 },
    "tile-0309": { "x": 240, "y": 96 },
    "tile-0310": { "x": 256, "y": 96 },
    "tile-0311": { "x": 272, "y": 96 },
    "tile-0312": { "x": 288, "y": 96 },
    "tile-0313": { "x": 304, "y": 96 },
    "tile-0314": { "x": 320, "y": 96 },
    "tile-0315": { "x": 336, "y": 96 },
    "tile-0316": { "x": 352, "y": 96 },
    "tile-0317": { "x": 368, "y": 96 },
    "tile-0318": { "x": 384, "y": 96 },
    "tile-0319": { "x": 400, "y": 96 },
    "tile-0320": { "x": 416, "y": 96 },
    "tile-0321": { "x": 432, "y": 96 },
    "tile-0322": { "x": 448, "y": 96 },
    "tile-0323": { "x": 464, "y": 96 },
    "tile-0324": { "x": 480, "y": 96 },
    "tile-0325": { "x": 496, "y": 96 },
    "tile-0326": { "x": 512, "y": 96 },
    "tile-0327": { "x": 528, "y": 96 },
    "tile-0328": { "x": 544, "y": 96 },
    "tile-0329": { "x": 560, "y": 96 },
    "tile-0330": { "x": 576, "y": 96 },
    "tile-0331": { "x": 592, "y": 96 },
    "tile-0332": { "x": 608, "y": 96 },
    "tile-0333": { "x": 624, "y": 96 },
    "tile-0334": { "x": 640, "y": 96 },
    "tile-0335": { "x": 656, "y": 96 },
    "tile-0336": { "x": 672, "y": 96 },
    "tile-0337": { "x": 688, "y": 96 },
    "tile-0338": { "x": 704, "y": 96 },
    "tile-0339": { "x": 720, "y": 96 },
    "tile-0340": { "x": 736, "y": 96 },
    "tile-0341": { "x": 752, "y": 96 },
    "tile-0342": { "x": 768, "y": 96 },
    "tile-0343": { "x": 0, "y": 112 },
    "tile-0344": { "x": 16, "y": 112 },
    "tile-0345": { "x": 32, "y": 112 },
    "tile-0346": { "x": 48, "y": 112 },
    "tile-0347": { "x": 64, "y": 112 },
    "tile-0348": { "x": 80, "y": 112 },
    "tile-0349": { "x": 96, "y": 112 },
    "tile-0350": { "x": 112, "y": 112 },
    "tile-0351": { "x": 128, "y": 112 },
    "tile-0352": { "x": 144, "y": 112 },
    "tile-0353": { "x": 160, "y": 112 },
    "tile-0354": { "x": 176, "y": 112 },
    "tile-0355": { "x": 192, "y": 112 },
    "tile-0356": { "x": 208, "y": 112 },
    "tile-0357": { "x": 224, "y": 112 },
    "tile-0358": { "x": 240, "y": 112 },
    "tile-0359": { "x": 256, "y": 112 },
    "tile-0360": { "x": 272, "y": 112 },
    "tile-0361": { "x": 288, "y": 112 },
    "tile-0362": { "x": 304, "y": 112 },
    "tile-0363": { "x": 320, "y": 112 },
    "tile-0364": { "x": 336, "y": 112 },
    "tile-0365": { "x": 352, "y": 112 },
    "tile-0366": { "x": 368, "y": 112 },
    "tile-0367": { "x": 384, "y": 112 },
    "tile-0368": { "x": 400, "y": 112 },
    "tile-0369": { "x": 416, "y": 112 },
    "tile-0370": { "x": 432, "y": 112 },
    "tile-0371": { "x": 448, "y": 112 },
    "tile-0372": { "x": 464, "y": 112 },
    "tile-0373": { "x": 480, "y": 112 },
    "tile-0374": { "x": 496, "y": 112 },
    "tile-0375": { "x": 512, "y": 112 },
    "tile-0376": { "x": 528, "y": 112 },
    "tile-0377": { "x": 544, "y": 112 },
    "tile-0378": { "x": 560, "y": 112 },
    "tile-0379": { "x": 576, "y": 112 },
    "tile-0380": { "x": 592, "y": 112 },
    "tile-0381": { "x": 608, "y": 112 },
    "tile-0382": { "x": 624, "y": 112 },
    "tile-0383": { "x": 640, "y": 112 },
    "tile-0384": { "x": 656, "y": 112 },
    "tile-0385": { "x": 672, "y": 112 },
    "tile-0386": { "x": 688, "y": 112 },
    "tile-0387": { "x": 704, "y": 112 },
    "tile-0388": { "x": 720, "y": 112 },
    "tile-0389": { "x": 736, "y": 112 },
    "tile-0390": { "x": 752, "y": 112 },
    "tile-0391": { "x": 768, "y": 112 },
    "tile-0392": { "x": 0, "y": 128 },
    "tile-0393": { "x": 16, "y": 128 },
    "tile-0394": { "x": 32, "y": 128 },
    "tile-0395": { "x": 48, "y": 128 },
    "tile-0396": { "x": 64, "y": 128 },
    "tile-0397": { "x": 80, "y": 128 },
    "tile-0398": { "x": 96, "y": 128 },
    "tile-0399": { "x": 112, "y": 128 },
    "tile-0400": { "x": 128, "y": 128 },
    "tile-0401": { "x": 144, "y": 128 },
    "tile-0402": { "x": 160, "y": 128 },
    "tile-0403": { "x": 176, "y": 128 },
    "tile-0404": { "x": 192, "y": 128 },
    "tile-0405": { "x": 208, "y": 128 },
    "tile-0406": { "x": 224, "y": 128 },
    "tile-0407": { "x": 240, "y": 128 },
    "tile-0408": { "x": 256, "y": 128 },
    "tile-0409": { "x": 272, "y": 128 },
    "tile-0410": { "x": 288, "y": 128 },
    "tile-0411": { "x": 304, "y": 128 },
    "tile-0412": { "x": 320, "y": 128 },
    "tile-0413": { "x": 336, "y": 128 },
    "tile-0414": { "x": 352, "y": 128 },
    "tile-0415": { "x": 368, "y": 128 },
    "tile-0416": { "x": 384, "y": 128 },
    "tile-0417": { "x": 400, "y": 128 },
    "tile-0418": { "x": 416, "y": 128 },
    "tile-0419": { "x": 432, "y": 128 },
    "tile-0420": { "x": 448, "y": 128 },
    "tile-0421": { "x": 464, "y": 128 },
    "tile-0422": { "x": 480, "y": 128 },
    "tile-0423": { "x": 496, "y": 128 },
    "tile-0424": { "x": 512, "y": 128 },
    "tile-0425": { "x": 528, "y": 128 },
    "tile-0426": { "x": 544, "y": 128 },
    "tile-0427": { "x": 560, "y": 128 },
    "tile-0428": { "x": 576, "y": 128 },
    "tile-0429": { "x": 592, "y": 128 },
    "tile-0430": { "x": 608, "y": 128 },
    "tile-0431": { "x": 624, "y": 128 },
    "tile-0432": { "x": 640, "y": 128 },
    "tile-0433": { "x": 656, "y": 128 },
    "tile-0434": { "x": 672, "y": 128 },
    "tile-0435": { "x": 688, "y": 128 },
    "tile-0436": { "x": 704, "y": 128 },
    "tile-0437": { "x": 720, "y": 128 },
    "tile-0438": { "x": 736, "y": 128 },
    "tile-0439": { "x": 752, "y": 128 },
    "tile-0440": { "x": 768, "y": 128 },
    "tile-0441": { "x": 0, "y": 144 },
    "tile-0442": { "x": 16, "y": 144 },
    "tile-0443": { "x": 32, "y": 144 },
    "tile-0444": { "x": 48, "y": 144 },
    "tile-0445": { "x": 64, "y": 144 },
    "tile-0446": { "x": 80, "y": 144 },
    "tile-0447": { "x": 96, "y": 144 },
    "tile-0448": { "x": 112, "y": 144 },
    "tile-0449": { "x": 128, "y": 144 },
    "tile-0450": { "x": 144, "y": 144 },
    "tile-0451": { "x": 160, "y": 144 },
    "tile-0452": { "x": 176, "y": 144 },
    "tile-0453": { "x": 192, "y": 144 },
    "tile-0454": { "x": 208, "y": 144 },
    "tile-0455": { "x": 224, "y": 144 },
    "tile-0456": { "x": 240, "y": 144 },
    "tile-0457": { "x": 256, "y": 144 },
    "tile-0458": { "x": 272, "y": 144 },
    "tile-0459": { "x": 288, "y": 144 },
    "tile-0460": { "x": 304, "y": 144 },
    "tile-0461": { "x": 320, "y": 144 },
    "tile-0462": { "x": 336, "y": 144 },
    "tile-0463": { "x": 352, "y": 144 },
    "tile-0464": { "x": 368, "y": 144 },
    "tile-0465": { "x": 384, "y": 144 },
    "tile-0466": { "x": 400, "y": 144 },
    "tile-0467": { "x": 416, "y": 144 },
    "tile-0468": { "x": 432, "y": 144 },
    "tile-0469": { "x": 448, "y": 144 },
    "tile-0470": { "x": 464, "y": 144 },
    "tile-0471": { "x": 480, "y": 144 },
    "tile-0472": { "x": 496, "y": 144 },
    "tile-0473": { "x": 512, "y": 144 },
    "tile-0474": { "x": 528, "y": 144 },
    "tile-0475": { "x": 544, "y": 144 },
    "tile-0476": { "x": 560, "y": 144 },
    "tile-0477": { "x": 576, "y": 144 },
    "tile-0478": { "x": 592, "y": 144 },
    "tile-0479": { "x": 608, "y": 144 },
    "tile-0480": { "x": 624, "y": 144 },
    "tile-0481": { "x": 640, "y": 144 },
    "tile-0482": { "x": 656, "y": 144 },
    "tile-0483": { "x": 672, "y": 144 },
    "tile-0484": { "x": 688, "y": 144 },
    "tile-0485": { "x": 704, "y": 144 },
    "tile-0486": { "x": 720, "y": 144 },
    "tile-0487": { "x": 736, "y": 144 },
    "tile-0488": { "x": 752, "y": 144 },
    "tile-0489": { "x": 768, "y": 144 },
    "tile-0490": { "x": 0, "y": 160 },
    "tile-0491": { "x": 16, "y": 160 },
    "tile-0492": { "x": 32, "y": 160 },
    "tile-0493": { "x": 48, "y": 160 },
    "tile-0494": { "x": 64, "y": 160 },
    "tile-0495": { "x": 80, "y": 160 },
    "tile-0496": { "x": 96, "y": 160 },
    "tile-0497": { "x": 112, "y": 160 },
    "tile-0498": { "x": 128, "y": 160 },
    "tile-0499": { "x": 144, "y": 160 },
    "tile-0500": { "x": 160, "y": 160 },
    "tile-0501": { "x": 176, "y": 160 },
    "tile-0502": { "x": 192, "y": 160 },
    "tile-0503": { "x": 208, "y": 160 },
    "tile-0504": { "x": 224, "y": 160 },
    "tile-0505": { "x": 240, "y": 160 },
    "tile-0506": { "x": 256, "y": 160 },
    "tile-0507": { "x": 272, "y": 160 },
    "tile-0508": { "x": 288, "y": 160 },
    "tile-0509": { "x": 304, "y": 160 },
    "tile-0510": { "x": 320, "y": 160 },
    "tile-0511": { "x": 336, "y": 160 },
    "tile-0512": { "x": 352, "y": 160 },
    "tile-0513": { "x": 368, "y": 160 },
    "tile-0514": { "x": 384, "y": 160 },
    "tile-0515": { "x": 400, "y": 160 },
    "tile-0516": { "x": 416, "y": 160 },
    "tile-0517": { "x": 432, "y": 160 },
    "tile-0518": { "x": 448, "y": 160 },
    "tile-0519": { "x": 464, "y": 160 },
    "tile-0520": { "x": 480, "y": 160 },
    "tile-0521": { "x": 496, "y": 160 },
    "tile-0522": { "x": 512, "y": 160 },
    "tile-0523": { "x": 528, "y": 160 },
    "tile-0524": { "x": 544, "y": 160 },
    "tile-0525": { "x": 560, "y": 160 },
    "tile-0526": { "x": 576, "y": 160 },
    "tile-0527": { "x": 592, "y": 160 },
    "tile-0528": { "x": 608, "y": 160 },
    "tile-0529": { "x": 624, "y": 160 },
    "tile-0530": { "x": 640, "y": 160 },
    "tile-0531": { "x": 656, "y": 160 },
    "tile-0532": { "x": 672, "y": 160 },
    "tile-0533": { "x": 688, "y": 160 },
    "tile-0534": { "x": 704, "y": 160 },
    "tile-0535": { "x": 720, "y": 160 },
    "tile-0536": { "x": 736, "y": 160 },
    "tile-0537": { "x": 752, "y": 160 },
    "tile-0538": { "x": 768, "y": 160 },
    "tile-0539": { "x": 0, "y": 176 },
    "tile-0540": { "x": 16, "y": 176 },
    "tile-0541": { "x": 32, "y": 176 },
    "tile-0542": { "x": 48, "y": 176 },
    "tile-0543": { "x": 64, "y": 176 },
    "tile-0544": { "x": 80, "y": 176 },
    "tile-0545": { "x": 96, "y": 176 },
    "tile-0546": { "x": 112, "y": 176 },
    "tile-0547": { "x": 128, "y": 176 },
    "tile-0548": { "x": 144, "y": 176 },
    "tile-0549": { "x": 160, "y": 176 },
    "tile-0550": { "x": 176, "y": 176 },
    "tile-0551": { "x": 192, "y": 176 },
    "tile-0552": { "x": 208, "y": 176 },
    "tile-0553": { "x": 224, "y": 176 },
    "tile-0554": { "x": 240, "y": 176 },
    "tile-0555": { "x": 256, "y": 176 },
    "tile-0556": { "x": 272, "y": 176 },
    "tile-0557": { "x": 288, "y": 176 },
    "tile-0558": { "x": 304, "y": 176 },
    "tile-0559": { "x": 320, "y": 176 },
    "tile-0560": { "x": 336, "y": 176 },
    "tile-0561": { "x": 352, "y": 176 },
    "tile-0562": { "x": 368, "y": 176 },
    "tile-0563": { "x": 384, "y": 176 },
    "tile-0564": { "x": 400, "y": 176 },
    "tile-0565": { "x": 416, "y": 176 },
    "tile-0566": { "x": 432, "y": 176 },
    "tile-0567": { "x": 448, "y": 176 },
    "tile-0568": { "x": 464, "y": 176 },
    "tile-0569": { "x": 480, "y": 176 },
    "tile-0570": { "x": 496, "y": 176 },
    "tile-0571": { "x": 512, "y": 176 },
    "tile-0572": { "x": 528, "y": 176 },
    "tile-0573": { "x": 544, "y": 176 },
    "tile-0574": { "x": 560, "y": 176 },
    "tile-0575": { "x": 576, "y": 176 },
    "tile-0576": { "x": 592, "y": 176 },
    "tile-0577": { "x": 608, "y": 176 },
    "tile-0578": { "x": 624, "y": 176 },
    "tile-0579": { "x": 640, "y": 176 },
    "tile-0580": { "x": 656, "y": 176 },
    "tile-0581": { "x": 672, "y": 176 },
    "tile-0582": { "x": 688, "y": 176 },
    "tile-0583": { "x": 704, "y": 176 },
    "tile-0584": { "x": 720, "y": 176 },
    "tile-0585": { "x": 736, "y": 176 },
    "tile-0586": { "x": 752, "y": 176 },
    "tile-0587": { "x": 768, "y": 176 },
    "tile-0588": { "x": 0, "y": 192 },
    "tile-0589": { "x": 16, "y": 192 },
    "tile-0590": { "x": 32, "y": 192 },
    "tile-0591": { "x": 48, "y": 192 },
    "tile-0592": { "x": 64, "y": 192 },
    "tile-0593": { "x": 80, "y": 192 },
    "tile-0594": { "x": 96, "y": 192 },
    "tile-0595": { "x": 112, "y": 192 },
    "tile-0596": { "x": 128, "y": 192 },
    "tile-0597": { "x": 144, "y": 192 },
    "tile-0598": { "x": 160, "y": 192 },
    "tile-0599": { "x": 176, "y": 192 },
    "tile-0600": { "x": 192, "y": 192 },
    "tile-0601": { "x": 208, "y": 192 },
    "tile-0602": { "x": 224, "y": 192 },
    "tile-0603": { "x": 240, "y": 192 },
    "tile-0604": { "x": 256, "y": 192 },
    "tile-0605": { "x": 272, "y": 192 },
    "tile-0606": { "x": 288, "y": 192 },
    "tile-0607": { "x": 304, "y": 192 },
    "tile-0608": { "x": 320, "y": 192 },
    "tile-0609": { "x": 336, "y": 192 },
    "tile-0610": { "x": 352, "y": 192 },
    "tile-0611": { "x": 368, "y": 192 },
    "tile-0612": { "x": 384, "y": 192 },
    "tile-0613": { "x": 400, "y": 192 },
    "tile-0614": { "x": 416, "y": 192 },
    "tile-0615": { "x": 432, "y": 192 },
    "tile-0616": { "x": 448, "y": 192 },
    "tile-0617": { "x": 464, "y": 192 },
    "tile-0618": { "x": 480, "y": 192 },
    "tile-0619": { "x": 496, "y": 192 },
    "tile-0620": { "x": 512, "y": 192 },
    "tile-0621": { "x": 528, "y": 192 },
    "tile-0622": { "x": 544, "y": 192 },
    "tile-0623": { "x": 560, "y": 192 },
    "tile-0624": { "x": 576, "y": 192 },
    "tile-0625": { "x": 592, "y": 192 },
    "tile-0626": { "x": 608, "y": 192 },
    "tile-0627": { "x": 624, "y": 192 },
    "tile-0628": { "x": 640, "y": 192 },
    "tile-0629": { "x": 656, "y": 192 },
    "tile-0630": { "x": 672, "y": 192 },
    "tile-0631": { "x": 688, "y": 192 },
    "tile-0632": { "x": 704, "y": 192 },
    "tile-0633": { "x": 720, "y": 192 },
    "tile-0634": { "x": 736, "y": 192 },
    "tile-0635": { "x": 752, "y": 192 },
    "tile-0636": { "x": 768, "y": 192 },
    "tile-0637": { "x": 0, "y": 208 },
    "tile-0638": { "x": 16, "y": 208 },
    "tile-0639": { "x": 32, "y": 208 },
    "tile-0640": { "x": 48, "y": 208 },
    "tile-0641": { "x": 64, "y": 208 },
    "tile-0642": { "x": 80, "y": 208 },
    "tile-0643": { "x": 96, "y": 208 },
    "tile-0644": { "x": 112, "y": 208 },
    "tile-0645": { "x": 128, "y": 208 },
    "tile-0646": { "x": 144, "y": 208 },
    "tile-0647": { "x": 160, "y": 208 },
    "tile-0648": { "x": 176, "y": 208 },
    "tile-0649": { "x": 192, "y": 208 },
    "tile-0650": { "x": 208, "y": 208 },
    "tile-0651": { "x": 224, "y": 208 },
    "tile-0652": { "x": 240, "y": 208 },
    "tile-0653": { "x": 256, "y": 208 },
    "tile-0654": { "x": 272, "y": 208 },
    "tile-0655": { "x": 288, "y": 208 },
    "tile-0656": { "x": 304, "y": 208 },
    "tile-0657": { "x": 320, "y": 208 },
    "tile-0658": { "x": 336, "y": 208 },
    "tile-0659": { "x": 352, "y": 208 },
    "tile-0660": { "x": 368, "y": 208 },
    "tile-0661": { "x": 384, "y": 208 },
    "tile-0662": { "x": 400, "y": 208 },
    "tile-0663": { "x": 416, "y": 208 },
    "tile-0664": { "x": 432, "y": 208 },
    "tile-0665": { "x": 448, "y": 208 },
    "tile-0666": { "x": 464, "y": 208 },
    "tile-0667": { "x": 480, "y": 208 },
    "tile-0668": { "x": 496, "y": 208 },
    "tile-0669": { "x": 512, "y": 208 },
    "tile-0670": { "x": 528, "y": 208 },
    "tile-0671": { "x": 544, "y": 208 },
    "tile-0672": { "x": 560, "y": 208 },
    "tile-0673": { "x": 576, "y": 208 },
    "tile-0674": { "x": 592, "y": 208 },
    "tile-0675": { "x": 608, "y": 208 },
    "tile-0676": { "x": 624, "y": 208 },
    "tile-0677": { "x": 640, "y": 208 },
    "tile-0678": { "x": 656, "y": 208 },
    "tile-0679": { "x": 672, "y": 208 },
    "tile-0680": { "x": 688, "y": 208 },
    "tile-0681": { "x": 704, "y": 208 },
    "tile-0682": { "x": 720, "y": 208 },
    "tile-0683": { "x": 736, "y": 208 },
    "tile-0684": { "x": 752, "y": 208 },
    "tile-0685": { "x": 768, "y": 208 },
    "tile-0686": { "x": 0, "y": 224 },
    "tile-0687": { "x": 16, "y": 224 },
    "tile-0688": { "x": 32, "y": 224 },
    "tile-0689": { "x": 48, "y": 224 },
    "tile-0690": { "x": 64, "y": 224 },
    "tile-0691": { "x": 80, "y": 224 },
    "tile-0692": { "x": 96, "y": 224 },
    "tile-0693": { "x": 112, "y": 224 },
    "tile-0694": { "x": 128, "y": 224 },
    "tile-0695": { "x": 144, "y": 224 },
    "tile-0696": { "x": 160, "y": 224 },
    "tile-0697": { "x": 176, "y": 224 },
    "tile-0698": { "x": 192, "y": 224 },
    "tile-0699": { "x": 208, "y": 224 },
    "tile-0700": { "x": 224, "y": 224 },
    "tile-0701": { "x": 240, "y": 224 },
    "tile-0702": { "x": 256, "y": 224 },
    "tile-0703": { "x": 272, "y": 224 },
    "tile-0704": { "x": 288, "y": 224 },
    "tile-0705": { "x": 304, "y": 224 },
    "tile-0706": { "x": 320, "y": 224 },
    "tile-0707": { "x": 336, "y": 224 },
    "tile-0708": { "x": 352, "y": 224 },
    "tile-0709": { "x": 368, "y": 224 },
    "tile-0710": { "x": 384, "y": 224 },
    "tile-0711": { "x": 400, "y": 224 },
    "tile-0712": { "x": 416, "y": 224 },
    "tile-0713": { "x": 432, "y": 224 },
    "tile-0714": { "x": 448, "y": 224 },
    "tile-0715": { "x": 464, "y": 224 },
    "tile-0716": { "x": 480, "y": 224 },
    "tile-0717": { "x": 496, "y": 224 },
    "tile-0718": { "x": 512, "y": 224 },
    "tile-0719": { "x": 528, "y": 224 },
    "tile-0720": { "x": 544, "y": 224 },
    "tile-0721": { "x": 560, "y": 224 },
    "tile-0722": { "x": 576, "y": 224 },
    "tile-0723": { "x": 592, "y": 224 },
    "tile-0724": { "x": 608, "y": 224 },
    "tile-0725": { "x": 624, "y": 224 },
    "tile-0726": { "x": 640, "y": 224 },
    "tile-0727": { "x": 656, "y": 224 },
    "tile-0728": { "x": 672, "y": 224 },
    "tile-0729": { "x": 688, "y": 224 },
    "tile-0730": { "x": 704, "y": 224 },
    "tile-0731": { "x": 720, "y": 224 },
    "tile-0732": { "x": 736, "y": 224 },
    "tile-0733": { "x": 752, "y": 224 },
    "tile-0734": { "x": 768, "y": 224 },
    "tile-0735": { "x": 0, "y": 240 },
    "tile-0736": { "x": 16, "y": 240 },
    "tile-0737": { "x": 32, "y": 240 },
    "tile-0738": { "x": 48, "y": 240 },
    "tile-0739": { "x": 64, "y": 240 },
    "tile-0740": { "x": 80, "y": 240 },
    "tile-0741": { "x": 96, "y": 240 },
    "tile-0742": { "x": 112, "y": 240 },
    "tile-0743": { "x": 128, "y": 240 },
    "tile-0744": { "x": 144, "y": 240 },
    "tile-0745": { "x": 160, "y": 240 },
    "tile-0746": { "x": 176, "y": 240 },
    "tile-0747": { "x": 192, "y": 240 },
    "tile-0748": { "x": 208, "y": 240 },
    "tile-0749": { "x": 224, "y": 240 },
    "tile-0750": { "x": 240, "y": 240 },
    "tile-0751": { "x": 256, "y": 240 },
    "tile-0752": { "x": 272, "y": 240 },
    "tile-0753": { "x": 288, "y": 240 },
    "tile-0754": { "x": 304, "y": 240 },
    "tile-0755": { "x": 320, "y": 240 },
    "tile-0756": { "x": 336, "y": 240 },
    "tile-0757": { "x": 352, "y": 240 },
    "tile-0758": { "x": 368, "y": 240 },
    "tile-0759": { "x": 384, "y": 240 },
    "tile-0760": { "x": 400, "y": 240 },
    "tile-0761": { "x": 416, "y": 240 },
    "tile-0762": { "x": 432, "y": 240 },
    "tile-0763": { "x": 448, "y": 240 },
    "tile-0764": { "x": 464, "y": 240 },
    "tile-0765": { "x": 480, "y": 240 },
    "tile-0766": { "x": 496, "y": 240 },
    "tile-0767": { "x": 512, "y": 240 },
    "tile-0768": { "x": 528, "y": 240 },
    "tile-0769": { "x": 544, "y": 240 },
    "tile-0770": { "x": 560, "y": 240 },
    "tile-0771": { "x": 576, "y": 240 },
    "tile-0772": { "x": 592, "y": 240 },
    "tile-0773": { "x": 608, "y": 240 },
    "tile-0774": { "x": 624, "y": 240 },
    "tile-0775": { "x": 640, "y": 240 },
    "tile-0776": { "x": 656, "y": 240 },
    "tile-0777": { "x": 672, "y": 240 },
    "tile-0778": { "x": 688, "y": 240 },
    "tile-0779": { "x": 704, "y": 240 },
    "tile-0780": { "x": 720, "y": 240 },
    "tile-0781": { "x": 736, "y": 240 },
    "tile-0782": { "x": 752, "y": 240 },
    "tile-0783": { "x": 768, "y": 240 },
    "tile-0784": { "x": 0, "y": 256 },
    "tile-0785": { "x": 16, "y": 256 },
    "tile-0786": { "x": 32, "y": 256 },
    "tile-0787": { "x": 48, "y": 256 },
    "tile-0788": { "x": 64, "y": 256 },
    "tile-0789": { "x": 80, "y": 256 },
    "tile-0790": { "x": 96, "y": 256 },
    "tile-0791": { "x": 112, "y": 256 },
    "tile-0792": { "x": 128, "y": 256 },
    "tile-0793": { "x": 144, "y": 256 },
    "tile-0794": { "x": 160, "y": 256 },
    "tile-0795": { "x": 176, "y": 256 },
    "tile-0796": { "x": 192, "y": 256 },
    "tile-0797": { "x": 208, "y": 256 },
    "tile-0798": { "x": 224, "y": 256 },
    "tile-0799": { "x": 240, "y": 256 },
    "tile-0800": { "x": 256, "y": 256 },
    "tile-0801": { "x": 272, "y": 256 },
    "tile-0802": { "x": 288, "y": 256 },
    "tile-0803": { "x": 304, "y": 256 },
    "tile-0804": { "x": 320, "y": 256 },
    "tile-0805": { "x": 336, "y": 256 },
    "tile-0806": { "x": 352, "y": 256 },
    "tile-0807": { "x": 368, "y": 256 },
    "tile-0808": { "x": 384, "y": 256 },
    "tile-0809": { "x": 400, "y": 256 },
    "tile-0810": { "x": 416, "y": 256 },
    "tile-0811": { "x": 432, "y": 256 },
    "tile-0812": { "x": 448, "y": 256 },
    "tile-0813": { "x": 464, "y": 256 },
    "tile-0814": { "x": 480, "y": 256 },
    "tile-0815": { "x": 496, "y": 256 },
    "tile-0816": { "x": 512, "y": 256 },
    "tile-0817": { "x": 528, "y": 256 },
    "tile-0818": { "x": 544, "y": 256 },
    "tile-0819": { "x": 560, "y": 256 },
    "tile-0820": { "x": 576, "y": 256 },
    "tile-0821": { "x": 592, "y": 256 },
    "tile-0822": { "x": 608, "y": 256 },
    "tile-0823": { "x": 624, "y": 256 },
    "tile-0824": { "x": 640, "y": 256 },
    "tile-0825": { "x": 656, "y": 256 },
    "tile-0826": { "x": 672, "y": 256 },
    "tile-0827": { "x": 688, "y": 256 },
    "tile-0828": { "x": 704, "y": 256 },
    "tile-0829": { "x": 720, "y": 256 },
    "tile-0830": { "x": 736, "y": 256 },
    "tile-0831": { "x": 752, "y": 256 },
    "tile-0832": { "x": 768, "y": 256 },
    "tile-0833": { "x": 0, "y": 272 },
    "tile-0834": { "x": 16, "y": 272 },
    "tile-0835": { "x": 32, "y": 272 },
    "tile-0836": { "x": 48, "y": 272 },
    "tile-0837": { "x": 64, "y": 272 },
    "tile-0838": { "x": 80, "y": 272 },
    "tile-0839": { "x": 96, "y": 272 },
    "tile-0840": { "x": 112, "y": 272 },
    "tile-0841": { "x": 128, "y": 272 },
    "tile-0842": { "x": 144, "y": 272 },
    "tile-0843": { "x": 160, "y": 272 },
    "tile-0844": { "x": 176, "y": 272 },
    "tile-0845": { "x": 192, "y": 272 },
    "tile-0846": { "x": 208, "y": 272 },
    "tile-0847": { "x": 224, "y": 272 },
    "tile-0848": { "x": 240, "y": 272 },
    "tile-0849": { "x": 256, "y": 272 },
    "tile-0850": { "x": 272, "y": 272 },
    "tile-0851": { "x": 288, "y": 272 },
    "tile-0852": { "x": 304, "y": 272 },
    "tile-0853": { "x": 320, "y": 272 },
    "tile-0854": { "x": 336, "y": 272 },
    "tile-0855": { "x": 352, "y": 272 },
    "tile-0856": { "x": 368, "y": 272 },
    "tile-0857": { "x": 384, "y": 272 },
    "tile-0858": { "x": 400, "y": 272 },
    "tile-0859": { "x": 416, "y": 272 },
    "tile-0860": { "x": 432, "y": 272 },
    "tile-0861": { "x": 448, "y": 272 },
    "tile-0862": { "x": 464, "y": 272 },
    "tile-0863": { "x": 480, "y": 272 },
    "tile-0864": { "x": 496, "y": 272 },
    "tile-0865": { "x": 512, "y": 272 },
    "tile-0866": { "x": 528, "y": 272 },
    "tile-0867": { "x": 544, "y": 272 },
    "tile-0868": { "x": 560, "y": 272 },
    "tile-0869": { "x": 576, "y": 272 },
    "tile-0870": { "x": 592, "y": 272 },
    "tile-0871": { "x": 608, "y": 272 },
    "tile-0872": { "x": 624, "y": 272 },
    "tile-0873": { "x": 640, "y": 272 },
    "tile-0874": { "x": 656, "y": 272 },
    "tile-0875": { "x": 672, "y": 272 },
    "tile-0876": { "x": 688, "y": 272 },
    "tile-0877": { "x": 704, "y": 272 },
    "tile-0878": { "x": 720, "y": 272 },
    "tile-0879": { "x": 736, "y": 272 },
    "tile-0880": { "x": 752, "y": 272 },
    "tile-0881": { "x": 768, "y": 272 },
    "tile-0882": { "x": 0, "y": 288 },
    "tile-0883": { "x": 16, "y": 288 },
    "tile-0884": { "x": 32, "y": 288 },
    "tile-0885": { "x": 48, "y": 288 },
    "tile-0886": { "x": 64, "y": 288 },
    "tile-0887": { "x": 80, "y": 288 },
    "tile-0888": { "x": 96, "y": 288 },
    "tile-0889": { "x": 112, "y": 288 },
    "tile-0890": { "x": 128, "y": 288 },
    "tile-0891": { "x": 144, "y": 288 },
    "tile-0892": { "x": 160, "y": 288 },
    "tile-0893": { "x": 176, "y": 288 },
    "tile-0894": { "x": 192, "y": 288 },
    "tile-0895": { "x": 208, "y": 288 },
    "tile-0896": { "x": 224, "y": 288 },
    "tile-0897": { "x": 240, "y": 288 },
    "tile-0898": { "x": 256, "y": 288 },
    "tile-0899": { "x": 272, "y": 288 },
    "tile-0900": { "x": 288, "y": 288 },
    "tile-0901": { "x": 304, "y": 288 },
    "tile-0902": { "x": 320, "y": 288 },
    "tile-0903": { "x": 336, "y": 288 },
    "tile-0904": { "x": 352, "y": 288 },
    "tile-0905": { "x": 368, "y": 288 },
    "tile-0906": { "x": 384, "y": 288 },
    "tile-0907": { "x": 400, "y": 288 },
    "tile-0908": { "x": 416, "y": 288 },
    "tile-0909": { "x": 432, "y": 288 },
    "tile-0910": { "x": 448, "y": 288 },
    "tile-0911": { "x": 464, "y": 288 },
    "tile-0912": { "x": 480, "y": 288 },
    "tile-0913": { "x": 496, "y": 288 },
    "tile-0914": { "x": 512, "y": 288 },
    "tile-0915": { "x": 528, "y": 288 },
    "tile-0916": { "x": 544, "y": 288 },
    "tile-0917": { "x": 560, "y": 288 },
    "tile-0918": { "x": 576, "y": 288 },
    "tile-0919": { "x": 592, "y": 288 },
    "tile-0920": { "x": 608, "y": 288 },
    "tile-0921": { "x": 624, "y": 288 },
    "tile-0922": { "x": 640, "y": 288 },
    "tile-0923": { "x": 656, "y": 288 },
    "tile-0924": { "x": 672, "y": 288 },
    "tile-0925": { "x": 688, "y": 288 },
    "tile-0926": { "x": 704, "y": 288 },
    "tile-0927": { "x": 720, "y": 288 },
    "tile-0928": { "x": 736, "y": 288 },
    "tile-0929": { "x": 752, "y": 288 },
    "tile-0930": { "x": 768, "y": 288 },
    "tile-0931": { "x": 0, "y": 304 },
    "tile-0932": { "x": 16, "y": 304 },
    "tile-0933": { "x": 32, "y": 304 },
    "tile-0934": { "x": 48, "y": 304 },
    "tile-0935": { "x": 64, "y": 304 },
    "tile-0936": { "x": 80, "y": 304 },
    "tile-0937": { "x": 96, "y": 304 },
    "tile-0938": { "x": 112, "y": 304 },
    "tile-0939": { "x": 128, "y": 304 },
    "tile-0940": { "x": 144, "y": 304 },
    "tile-0941": { "x": 160, "y": 304 },
    "tile-0942": { "x": 176, "y": 304 },
    "tile-0943": { "x": 192, "y": 304 },
    "tile-0944": { "x": 208, "y": 304 },
    "tile-0945": { "x": 224, "y": 304 },
    "tile-0946": { "x": 240, "y": 304 },
    "tile-0947": { "x": 256, "y": 304 },
    "tile-0948": { "x": 272, "y": 304 },
    "tile-0949": { "x": 288, "y": 304 },
    "tile-0950": { "x": 304, "y": 304 },
    "tile-0951": { "x": 320, "y": 304 },
    "tile-0952": { "x": 336, "y": 304 },
    "tile-0953": { "x": 352, "y": 304 },
    "tile-0954": { "x": 368, "y": 304 },
    "tile-0955": { "x": 384, "y": 304 },
    "tile-0956": { "x": 400, "y": 304 },
    "tile-0957": { "x": 416, "y": 304 },
    "tile-0958": { "x": 432, "y": 304 },
    "tile-0959": { "x": 448, "y": 304 },
    "tile-0960": { "x": 464, "y": 304 },
    "tile-0961": { "x": 480, "y": 304 },
    "tile-0962": { "x": 496, "y": 304 },
    "tile-0963": { "x": 512, "y": 304 },
    "tile-0964": { "x": 528, "y": 304 },
    "tile-0965": { "x": 544, "y": 304 },
    "tile-0966": { "x": 560, "y": 304 },
    "tile-0967": { "x": 576, "y": 304 },
    "tile-0968": { "x": 592, "y": 304 },
    "tile-0969": { "x": 608, "y": 304 },
    "tile-0970": { "x": 624, "y": 304 },
    "tile-0971": { "x": 640, "y": 304 },
    "tile-0972": { "x": 656, "y": 304 },
    "tile-0973": { "x": 672, "y": 304 },
    "tile-0974": { "x": 688, "y": 304 },
    "tile-0975": { "x": 704, "y": 304 },
    "tile-0976": { "x": 720, "y": 304 },
    "tile-0977": { "x": 736, "y": 304 },
    "tile-0978": { "x": 752, "y": 304 },
    "tile-0979": { "x": 768, "y": 304 },
    "tile-0980": { "x": 0, "y": 320 },
    "tile-0981": { "x": 16, "y": 320 },
    "tile-0982": { "x": 32, "y": 320 },
    "tile-0983": { "x": 48, "y": 320 },
    "tile-0984": { "x": 64, "y": 320 },
    "tile-0985": { "x": 80, "y": 320 },
    "tile-0986": { "x": 96, "y": 320 },
    "tile-0987": { "x": 112, "y": 320 },
    "tile-0988": { "x": 128, "y": 320 },
    "tile-0989": { "x": 144, "y": 320 },
    "tile-0990": { "x": 160, "y": 320 },
    "tile-0991": { "x": 176, "y": 320 },
    "tile-0992": { "x": 192, "y": 320 },
    "tile-0993": { "x": 208, "y": 320 },
    "tile-0994": { "x": 224, "y": 320 },
    "tile-0995": { "x": 240, "y": 320 },
    "tile-0996": { "x": 256, "y": 320 },
    "tile-0997": { "x": 272, "y": 320 },
    "tile-0998": { "x": 288, "y": 320 },
    "tile-0999": { "x": 304, "y": 320 },
    "tile-1000": { "x": 320, "y": 320 },
    "tile-1001": { "x": 336, "y": 320 },
    "tile-1002": { "x": 352, "y": 320 },
    "tile-1003": { "x": 368, "y": 320 },
    "tile-1004": { "x": 384, "y": 320 },
    "tile-1005": { "x": 400, "y": 320 },
    "tile-1006": { "x": 416, "y": 320 },
    "tile-1007": { "x": 432, "y": 320 },
    "tile-1008": { "x": 448, "y": 320 },
    "tile-1009": { "x": 464, "y": 320 },
    "tile-1010": { "x": 480, "y": 320 },
    "tile-1011": { "x": 496, "y": 320 },
    "tile-1012": { "x": 512, "y": 320 },
    "tile-1013": { "x": 528, "y": 320 },
    "tile-1014": { "x": 544, "y": 320 },
    "tile-1015": { "x": 560, "y": 320 },
    "tile-1016": { "x": 576, "y": 320 },
    "tile-1017": { "x": 592, "y": 320 },
    "tile-1018": { "x": 608, "y": 320 },
    "tile-1019": { "x": 624, "y": 320 },
    "tile-1020": { "x": 640, "y": 320 },
    "tile-1021": { "x": 656, "y": 320 },
    "tile-1022": { "x": 672, "y": 320 },
    "tile-1023": { "x": 688, "y": 320 },
    "tile-1024": { "x": 704, "y": 320 },
    "tile-1025": { "x": 720, "y": 320 },
    "tile-1026": { "x": 736, "y": 320 },
    "tile-1027": { "x": 752, "y": 320 },
    "tile-1028": { "x": 768, "y": 320 },
    "tile-1029": { "x": 0, "y": 336 },
    "tile-1030": { "x": 16, "y": 336 },
    "tile-1031": { "x": 32, "y": 336 },
    "tile-1032": { "x": 48, "y": 336 },
    "tile-1033": { "x": 64, "y": 336 },
    "tile-1034": { "x": 80, "y": 336 },
    "tile-1035": { "x": 96, "y": 336 },
    "tile-1036": { "x": 112, "y": 336 },
    "tile-1037": { "x": 128, "y": 336 },
    "tile-1038": { "x": 144, "y": 336 },
    "tile-1039": { "x": 160, "y": 336 },
    "tile-1040": { "x": 176, "y": 336 },
    "tile-1041": { "x": 192, "y": 336 },
    "tile-1042": { "x": 208, "y": 336 },
    "tile-1043": { "x": 224, "y": 336 },
    "tile-1044": { "x": 240, "y": 336 },
    "tile-1045": { "x": 256, "y": 336 },
    "tile-1046": { "x": 272, "y": 336 },
    "tile-1047": { "x": 288, "y": 336 },
    "tile-1048": { "x": 304, "y": 336 },
    "tile-1049": { "x": 320, "y": 336 },
    "tile-1050": { "x": 336, "y": 336 },
    "tile-1051": { "x": 352, "y": 336 },
    "tile-1052": { "x": 368, "y": 336 },
    "tile-1053": { "x": 384, "y": 336 },
    "tile-1054": { "x": 400, "y": 336 },
    "tile-1055": { "x": 416, "y": 336 },
    "tile-1056": { "x": 432, "y": 336 },
    "tile-1057": { "x": 448, "y": 336 },
    "tile-1058": { "x": 464, "y": 336 },
    "tile-1059": { "x": 480, "y": 336 },
    "tile-1060": { "x": 496, "y": 336 },
    "tile-1061": { "x": 512, "y": 336 },
    "tile-1062": { "x": 528, "y": 336 },
    "tile-1063": { "x": 544, "y": 336 },
    "tile-1064": { "x": 560, "y": 336 },
    "tile-1065": { "x": 576, "y": 336 },
    "tile-1066": { "x": 592, "y": 336 },
    "tile-1067": { "x": 608, "y": 336 },
    "tile-1068": { "x": 624, "y": 336 },
    "tile-1069": { "x": 640, "y": 336 },
    "tile-1070": { "x": 656, "y": 336 },
    "tile-1071": { "x": 672, "y": 336 },
    "tile-1072": { "x": 688, "y": 336 },
    "tile-1073": { "x": 704, "y": 336 },
    "tile-1074": { "x": 720, "y": 336 },
    "tile-1075": { "x": 736, "y": 336 },
    "tile-1076": { "x": 752, "y": 336 },
    "tile-1077": { "x": 768, "y": 336 }
  },

  "tags": {
    "platformer": ["tile-0000", "tile-0001", "tile-0002", "tile-0003", "tile-0049", "tile-0050", "tile-0051"],
    "interior": ["tile-0200", "tile-0201", "tile-0202", "tile-0249", "tile-0250"],
    "urban": ["tile-0400", "tile-0401", "tile-0402", "tile-0449", "tile-0450"],
    "fantasy": ["tile-0600", "tile-0601", "tile-0602", "tile-0649", "tile-0650"]
  }
}
